decrypt256/__init__.py
decrypt256/decrypt256.py
decrypt256-1.0.1.dist-info/LICENSE
decrypt256-1.0.1.dist-info/METADATA
decrypt256-1.0.1.dist-info/WHEEL
decrypt256-1.0.1.dist-info/top_level.txt
decrypt256-1.0.1.dist-info/RECORD
