Metadata-Version: 2.1
Name: decrypt256
Version: 1.0.1
Summary: A sha-256 decryptor
Home-page: https://github.com/101happy/decrypt256
Author: 101 happy
Author-email: ous.asist@gmail.com
License: UNKNOWN
Project-URL: Bug Tracker, https://github.com/101happy/decrypt256/issues
Platform: UNKNOWN
Classifier: Programming Language :: Python :: 3
Classifier: License :: OSI Approved :: MIT License
Classifier: Operating System :: OS Independent
Requires-Python: >=3.6
License-File: LICENSE
